setup.py
disciple/__init__.py
disciple.egg-info/PKG-INFO
disciple.egg-info/SOURCES.txt
disciple.egg-info/dependency_links.txt
disciple.egg-info/not-zip-safe
disciple.egg-info/requires.txt
disciple.egg-info/top_level.txt
disciple/contrib/__init__.py
disciple/contrib/channel_base.py
disciple/contrib/context.py
disciple/contrib/events.py
disciple/contrib/exceptions.py
disciple/contrib/gevent_zmq.py
disciple/contrib/socket.py
disciple/dealer/__init__.py
disciple/dealer/core.py
disciple/worker/__init__.py
disciple/worker/core.py
disciple/zoo/__init__.py
disciple/zoo/drone.py